Metadata-Version: 1.0
Name: ploopy
Version: 9
Summary: ploopyness
Home-page: UNKNOWN
Author: UNKNOWN
Author-email: UNKNOWN
License: UNKNOWN
Keywords: ploopy say
Platform: UNKNOWN
